{
  "9221329":"senador",
  "9221339":"senador",
  "9219560":"diputado",

  "9219498":"diputado",
  "9221526":"diputado",
  "9218432":"diputado",
  "9218607":"diputado",
  "9218386":"diputado",
  "9218885":"diputado",
  "9218900":"diputado",
  "9218902":"diputado",
  "9218909":"diputado",
  "9218938":"diputado",
  "9218958":"diputado",
  "9219022":"diputado",
  "9219044":"diputado",
  "9219454":"diputado",
  "9219495":"diputado",
  "9219721":"diputado",
  "9219725":"diputado",
  "9221503":"diputado",
  "9219122":"diputado",
  "9219561":"diputado",
  "9218453":"diputado",
  "9218992":"diputado",
  "9219116":"senador",
  "9221295":"senador",
  "9220522":"senador",
  "9220329":"senador",
  "9218840":"senador",
  "9219084":"senador",
  "9219086":"senador",
  "9220672":"senador",
  "9221290":"senador"
}
